dose/__init__.py
dose/__main__.py
dose/_legacy.py
dose/about.py
dose/compat.py
dose/help.py
dose/misc.py
dose/rest.py
dose/runner.py
dose/shared.py
dose/terminal.py
dose/watcher.py
dose-1.2.3.data/data/share/dose/v1.2.3/CHANGES.rst
dose-1.2.3.data/data/share/dose/v1.2.3/CONTRIBUTORS.txt
dose-1.2.3.data/data/share/dose/v1.2.3/COPYING.txt
dose-1.2.3.data/data/share/dose/v1.2.3/README.rst
dose-1.2.3.data/data/share/dose/v1.2.3/screenshot_cygwin.png
dose-1.2.3.data/data/share/dose/v1.2.3/screenshot_linux.png
dose-1.2.3.data/data/share/dose/v1.2.3/screenshot_osx.png
dose-1.2.3.data/data/share/dose/v1.2.3/screenshot_windows.png
dose-1.2.3.dist-info/COPYING.txt
dose-1.2.3.dist-info/METADATA
dose-1.2.3.dist-info/WHEEL
dose-1.2.3.dist-info/entry_points.txt
dose-1.2.3.dist-info/top_level.txt
dose-1.2.3.dist-info/RECORD
